pup/__init__.py
pup/http.py
pup/py.py
pup/sort.py
pup/xpath.py
pup_tools-3.0.0.dist-info/METADATA
pup_tools-3.0.0.dist-info/RECORD
pup_tools-3.0.0.dist-info/WHEEL
pup_tools-3.0.0.dist-info/entry_points.txt
pup_tools-3.0.0.dist-info/top_level.txt
