Metadata-Version: 2.1
Name: pup-tools
Version: 3.0.0
Summary: A collection of miscellaneous Python tools.
Home-page: https://github.com/duckinator/pup-tools
Author: Ellen Marie Dash
Author-email: me@duckie.co
License: MIT
Platform: UNKNOWN
Classifier: Programming Language :: Python :: 3
Classifier: License :: OSI Approved :: MIT License
Classifier: Operating System :: OS Independent
Requires-Python: >=3.5
Requires-Dist: astunparse
